symcodelib/__init__.py
symcodelib-0.1.dist-info/METADATA
symcodelib-0.1.dist-info/WHEEL
symcodelib-0.1.dist-info/top_level.txt
symcodelib-0.1.dist-info/RECORD
