Metadata-Version: 2.1
Name: symcodelib
Version: 0.1
Summary: This library is built to get stock codes in a format required while using SmartApi websocket
Author: Abhirath Dubey
Author-email: abhirathdubey2804@gmail.com
License: UNKNOWN
Platform: UNKNOWN
Requires-Dist: requests
